<?xml version="1.0" encoding="utf-8" ?>
<Defs>
	<RulePackDef>
		<defName>Mashed_Lynians_Namer_LynianNotes</defName>
		<include>
			<li>ArtNameUtility</li>
		</include>
		<rulePack>
			<rulesStrings>
				<!-- General -->
				<li>title->[authored_title]</li>
				<li>title->[regular_title]</li>
				<!-- non-Authored Books -->
				<li>regular_title->[regular_gen]</li>
				<li>regular_gen->[journalDescription] Notes on [subject_primary]</li>
				<li>regular_gen->[journalDescription] Notes on [subject_secondary]</li>
				<!-- Authored Books -->
				<li>authored_title->[author_gen]</li>
				<li>author_gen->[ANYPAWN_nameIndef]'s Notes on [subject_primary]</li>
				<li>author_gen->[ANYPAWN_nameIndef]'s Notes on [subject_secondary]</li>
				<!-- Notes description -->
				<li>journalDescription->scholars</li>
				<li>journalDescription->researchers</li>
			</rulesStrings>
		</rulePack>
	</RulePackDef>
</Defs>