<?xml version="1.0" encoding="utf-8"?>
<Defs>
	<AlienRace.RaceSettings>
		<defName>Mashed_Lynian_RaceSettings</defName>
		<pawnKindSettings>
			<!-- ==========[Slaves]==========-->
			<alienslavekinds>
				<li>
					<kindDefs>
						<li>Mashed_Lynian_FelyneTribesperson</li>
						<li>Mashed_Lynian_MelynxTribesperson</li>
						<li>Mashed_Lynian_GrimalkyneTribesperson</li>
					</kindDefs>
					<chance>5.0</chance>
				</li>
			</alienslavekinds>
			<!-- ==========[Refugees]==========-->
			<alienrefugeekinds>
				<li>
					<kindDefs>
						<li>Mashed_Lynian_FelyneTribesperson</li>
						<li>Mashed_Lynian_MelynxTribesperson</li>
						<li>Mashed_Lynian_GrimalkyneTribesperson</li>
					</kindDefs>
					<chance>10.0</chance>
				</li>
				<li>
					<kindDefs>
						<li>Mashed_Lynian_ShakalakaTribesperson</li>
						<li>Mashed_Lynian_GajalakaTribesperson</li>
						<li>Mashed_Lynian_BoaboaTribesperson</li>
						<li>Mashed_Lynian_UrukiTribesperson</li>
					</kindDefs>
					<chance>5.0</chance>
				</li>
			</alienrefugeekinds>
			<!-- ==========[Starting colonists]==========-->
			<startingColonists>
				<!-- ==========[Outlander]==========-->
				<li>
					<pawnKindEntries>
						<li>
							<kindDefs>
								<li>Mashed_Lynian_FelyneColonist</li>
								<li>Mashed_Lynian_MelynxColonist</li>
								<li>Mashed_Lynian_GrimalkyneColonist</li>
								<li>Mashed_Lynian_UrukiColonist</li>
							</kindDefs>
							<chance>5.0</chance>
						</li>
						<li>
							<kindDefs>
								<li>Mashed_Lynian_BoaboaColonist</li>
								<li>Mashed_Lynian_GajalakaColonist</li>
								<li>Mashed_Lynian_ShakalakaColonist</li>
							</kindDefs>
							<chance>0.5</chance>
						</li>
					</pawnKindEntries>
					<factionDefs>
						<li>PlayerColony</li>
					</factionDefs>
				</li>
				<!-- ==========[Tribal]==========-->
				<li>
					<pawnKindEntries>
						<li>
							<kindDefs>
								<li>Mashed_Lynian_FelyneTribesperson</li>
								<li>Mashed_Lynian_MelynxTribesperson</li>
								<li>Mashed_Lynian_GrimalkyneTribesperson</li>
							</kindDefs>
							<chance>5.0</chance>
						</li>
						<li>
							<kindDefs>
								<li>Mashed_Lynian_ShakalakaTribesperson</li>
								<li>Mashed_Lynian_GajalakaTribesperson</li>
								<li>Mashed_Lynian_BoaboaTribesperson</li>
								<li>Mashed_Lynian_UrukiTribesperson</li>
							</kindDefs>
							<chance>2.0</chance>
						</li>
					</pawnKindEntries>
					<factionDefs>
						<li>PlayerTribe</li>
					</factionDefs>
				</li>
				<!-- ==========[Lynians Felyne tribe]==========-->
				<li>
					<pawnKindEntries>
						<li>
							<kindDefs>
								<li>Mashed_Lynian_MelynxTribesperson</li>
							</kindDefs>
							<chance>5.0</chance>
						</li>
					</pawnKindEntries>
					<factionDefs>
						<li>Mashed_Lynian_FelynePlayerTribe</li>
						<li>Mashed_Lynian_FelynePlayerGuild</li>
					</factionDefs>
				</li>
				<!-- ==========[Lynians Felyne colony]==========-->
				<li>
					<pawnKindEntries>
						<li>
							<kindDefs>
								<li>Mashed_Lynian_MelynxColonist</li>
							</kindDefs>
							<chance>5.0</chance>
						</li>
						<li>
							<kindDefs>
								<li>Mashed_Lynian_GrimalkyneColonist</li>
							</kindDefs>
							<chance>5.0</chance>
						</li>
					</pawnKindEntries>
					<factionDefs>
						<li>Mashed_Lynian_FelynePlayerColony</li>
					</factionDefs>
				</li>
				<!-- ==========[Lynians Melynx tribe]==========-->
				<li>
					<pawnKindEntries>
						<li>
							<kindDefs>
								<li>Mashed_Lynian_FelyneTribesperson</li>
							</kindDefs>
							<chance>5.0</chance>
						</li>
					</pawnKindEntries>
					<factionDefs>
						<li>Mashed_Lynian_MelynxPlayerTribe</li>
						<li>Mashed_Lynian_MelynxPlayerGuild</li>
					</factionDefs>
				</li>
				<!-- ==========[Lynians Melynx colony]==========-->
				<li>
					<pawnKindEntries>
						<li>
							<kindDefs>
								<li>Mashed_Lynian_FelyneColonist</li>
							</kindDefs>
							<chance>5.0</chance>
						</li>
						<li>
							<kindDefs>
								<li>Mashed_Lynian_GrimalkyneColonist</li>
							</kindDefs>
							<chance>5.0</chance>
						</li>
					</pawnKindEntries>
					<factionDefs>
						<li>Mashed_Lynian_MelynxPlayerColony</li>
					</factionDefs>
				</li>
			</startingColonists>
			<!-- ==========[Wanderer joins]==========-->
			<alienwandererkinds>
				<!-- ==========[Vanilla player colony]==========-->
				<li>
					<pawnKindEntries>
						<li>
							<kindDefs>
								<li>Mashed_Lynian_FelyneColonist</li>
								<li>Mashed_Lynian_MelynxColonist</li>
								<li>Mashed_Lynian_GrimalkyneColonist</li>
								<li>Mashed_Lynian_UrukiColonist</li>
							</kindDefs>
							<chance>5.0</chance>
						</li>
					</pawnKindEntries>
					<factionDefs>
						<li>PlayerColony</li>
					</factionDefs>
				</li>
				<!-- ==========[Vanilla player tribe]==========-->
				<li>
					<pawnKindEntries>
						<li>
							<kindDefs>
								<li>Mashed_Lynian_FelyneTribesperson</li>
								<li>Mashed_Lynian_MelynxTribesperson</li>
								<li>Mashed_Lynian_GrimalkyneTribesperson</li>
								<li>Mashed_Lynian_UrukiTribesperson</li>
							</kindDefs>
							<chance>5.0</chance>
						</li>
						<li>
							<kindDefs>
								<li>Mashed_Lynian_GajalakaTribesperson</li>
								<li>Mashed_Lynian_BoaboaTribesperson</li>
							</kindDefs>
							<chance>2.0</chance>
						</li>
					</pawnKindEntries>
					<factionDefs>
						<li>PlayerTribe</li>
					</factionDefs>
				</li>
				<!-- ==========[Lynians Felyne tribe]==========-->
				<li>
					<pawnKindEntries>
						<li>
							<kindDefs>
								<li>Mashed_Lynian_FelyneTribesperson</li>
							</kindDefs>
							<chance>85.0</chance>
						</li>
						<li>
							<kindDefs>
								<li>Mashed_Lynian_MelynxTribesperson</li>
							</kindDefs>
							<chance>15.0</chance>
						</li>
						<li>
							<kindDefs>
								<li>Mashed_Lynian_GrimalkyneTribesperson</li>
								<li>Mashed_Lynian_UrukiTribesperson</li>
							</kindDefs>
							<chance>1.0</chance>
						</li>
					</pawnKindEntries>
					<factionDefs>
						<li>Mashed_Lynian_FelynePlayerTribe</li>
						<li>Mashed_Lynian_FelynePlayerGuild</li>
					</factionDefs>
				</li>
				<!-- ==========[Lynians Felyne colony]==========-->
				<li>
					<pawnKindEntries>
						<li>
							<kindDefs>
								<li>Mashed_Lynian_FelyneColonist</li>
							</kindDefs>
							<chance>80.0</chance>
						</li>
						<li>
							<kindDefs>
								<li>Mashed_Lynian_MelynxColonist</li>
							</kindDefs>
							<chance>15.0</chance>
						</li>
						<li>
							<kindDefs>
								<li>Mashed_Lynian_GrimalkyneColonist</li>
								<li>Mashed_Lynian_UrukiColonist</li>
							</kindDefs>
							<chance>5.0</chance>
						</li>
					</pawnKindEntries>
					<factionDefs>
						<li>Mashed_Lynian_FelynePlayerColony</li>
					</factionDefs>
				</li>
				<!-- ==========[Lynians Melynx tribe]==========-->
				<li>
					<pawnKindEntries>
						<li>
							<kindDefs>
								<li>Mashed_Lynian_MelynxTribesperson</li>
							</kindDefs>
							<chance>85.0</chance>
						</li>
						<li>
							<kindDefs>
								<li>Mashed_Lynian_FelyneTribesperson</li>
							</kindDefs>
							<chance>15.0</chance>
						</li>
						<li>
							<kindDefs>
								<li>Mashed_Lynian_GrimalkyneTribesperson</li>
								<li>Mashed_Lynian_UrukiTribesperson</li>
							</kindDefs>
							<chance>1.0</chance>
						</li>
					</pawnKindEntries>
					<factionDefs>
						<li>Mashed_Lynian_MelynxPlayerTribe</li>
						<li>Mashed_Lynian_MelynxPlayerGuild</li>
					</factionDefs>
				</li>
				<!-- ==========[Lynians Melynx colony]==========-->
				<li>
					<pawnKindEntries>
						<li>
							<kindDefs>
								<li>Mashed_Lynian_MelynxColonist</li>
							</kindDefs>
							<chance>80.0</chance>
						</li>
						<li>
							<kindDefs>
								<li>Mashed_Lynian_FelyneColonist</li>
							</kindDefs>
							<chance>15.0</chance>
						</li>
						<li>
							<kindDefs>
								<li>Mashed_Lynian_GrimalkyneColonist</li>
								<li>Mashed_Lynian_UrukiColonist</li>
							</kindDefs>
							<chance>5.0</chance>
						</li>
					</pawnKindEntries>
					<factionDefs>
						<li>Mashed_Lynian_MelynxPlayerColony</li>
					</factionDefs>
				</li>
				<!-- ==========[Lynians Grimalkyne tribe]==========-->
				<li>
					<pawnKindEntries>
						<li>
							<kindDefs>
								<li>Mashed_Lynian_GrimalkyneTribesperson</li>
							</kindDefs>
							<chance>90.0</chance>
						</li>
						<li>
							<kindDefs>
								<li>Mashed_Lynian_FelyneTribesperson</li>
								<li>Mashed_Lynian_MelynxTribesperson</li>
							</kindDefs>
							<chance>10.0</chance>
						</li>
						<li>
							<kindDefs>
								<li>Mashed_Lynian_UrukiTribesperson</li>
							</kindDefs>
							<chance>1.0</chance>
						</li>
					</pawnKindEntries>
					<factionDefs>
						<li>Mashed_Lynian_GrimalkynePlayerTribe</li>
						<li>Mashed_Lynian_GrimalkynePlayerGuild</li>
					</factionDefs>
				</li>
				<!-- ==========[Lynians Grimalkyne colony]==========-->
				<li>
					<pawnKindEntries>
						<li>
							<kindDefs>
								<li>Mashed_Lynian_GrimalkyneColonist</li>
							</kindDefs>
								<chance>85.0</chance>
						</li>
						<li>
							<kindDefs>
								<li>Mashed_Lynian_FelyneColonist</li>
								<li>Mashed_Lynian_MelynxColonist</li>
							</kindDefs>
							<chance>10.0</chance>
						</li>
						<li>
							<kindDefs>
								<li>Mashed_Lynian_UrukiColonist</li>
							</kindDefs>
							<chance>5.0</chance>
						</li>
					</pawnKindEntries>
					<factionDefs>
						<li>Mashed_Lynian_GrimalkynePlayerColony</li>
					</factionDefs>
				</li>
				<!-- ==========[Lynians Boaboa tribe]==========-->
				<li>
					<pawnKindEntries>
						<li>
							<kindDefs>
								<li>Mashed_Lynian_BoaboaTribesperson</li>
							</kindDefs>
							<chance>100.0</chance>
						</li>
					</pawnKindEntries>
					<factionDefs>
						<li>Mashed_Lynian_BoaboaPlayerTribe</li>
						<li>Mashed_Lynian_BoaboaPlayerGuild</li>
					</factionDefs>
				</li>
				<!-- ==========[Lynians Boaboa colony]==========-->
				<li>
					<pawnKindEntries>
						<li>
							<kindDefs>
								<li>Mashed_Lynian_BoaboaColonist</li>
							</kindDefs>
							<chance>100.0</chance>
						</li>
					</pawnKindEntries>
					<factionDefs>
						<li>Mashed_Lynian_BoaboaPlayerColony</li>
					</factionDefs>
				</li>
				<!-- ==========[Lynians Gajalaka tribe]==========-->
				<li>
					<pawnKindEntries>
						<li>
							<kindDefs>
								<li>Mashed_Lynian_GajalakaTribesperson</li>
							</kindDefs>
							<chance>100.0</chance>
						</li>
					</pawnKindEntries>
					<factionDefs>
						<li>Mashed_Lynian_GajalakaPlayerTribe</li>
						<li>Mashed_Lynian_GajalakaPlayerGuild</li>
					</factionDefs>
				</li>
				<!-- ==========[Lynians Gajalaka colony]==========-->
				<li>
					<pawnKindEntries>
						<li>
							<kindDefs>
								<li>Mashed_Lynian_GajalakaColonist</li>
							</kindDefs>
							<chance>100.0</chance>
						</li>
					</pawnKindEntries>
					<factionDefs>
						<li>Mashed_Lynian_GajalakaPlayerColony</li>
					</factionDefs>
				</li>
				<!-- ==========[Lynians Shakalaka tribe]==========-->
				<li>
					<pawnKindEntries>
						<li>
							<kindDefs>
								<li>Mashed_Lynian_ShakalakaTribesperson</li>
							</kindDefs>
							<chance>100.0</chance>
						</li>
					</pawnKindEntries>
					<factionDefs>
						<li>Mashed_Lynian_ShakalakaPlayerTribe</li>
						<li>Mashed_Lynian_ShakalakaPlayerGuild</li>
					</factionDefs>
				</li>
				<!-- ==========[Lynians Shakalaka colony]==========-->
				<li>
					<pawnKindEntries>
						<li>
							<kindDefs>
								<li>Mashed_Lynian_ShakalakaColonist</li>
							</kindDefs>
							<chance>100.0</chance>
						</li>
					</pawnKindEntries>
					<factionDefs>
						<li>Mashed_Lynian_ShakalakaPlayerColony</li>
					</factionDefs>
				</li>
				<!-- ==========[Lynians Uruki tribe]==========-->
				<li>
					<pawnKindEntries>
						<li>
							<kindDefs>
								<li>Mashed_Lynian_UrukiTribesperson</li>
							</kindDefs>
							<chance>100.0</chance>
						</li>
					</pawnKindEntries>
					<factionDefs>
						<li>Mashed_Lynian_UrukiPlayerTribe</li>
						<li>Mashed_Lynian_UrukiPlayerGuild</li>
					</factionDefs>
				</li>
				<!-- ==========[Lynians Uruki colony]==========-->
				<li>
					<pawnKindEntries>
						<li>
							<kindDefs>
								<li>Mashed_Lynian_UrukiColonist</li>
							</kindDefs>
							<chance>100.0</chance>
						</li>
					</pawnKindEntries>
					<factionDefs>
						<li>Mashed_Lynian_UrukiPlayerColony</li>
					</factionDefs>
				</li>
			</alienwandererkinds>
		</pawnKindSettings>
	</AlienRace.RaceSettings>
</Defs>